yourai/__init__.py
yourai/cli.py
yourai-0.0.4.dist-info/LICENSE
yourai-0.0.4.dist-info/METADATA
yourai-0.0.4.dist-info/WHEEL
yourai-0.0.4.dist-info/entry_points.txt
yourai-0.0.4.dist-info/top_level.txt
yourai-0.0.4.dist-info/RECORD
